LICENSE
MANIFEST.in
README.rst
setup.py
avalara/__init__.py
avalara/admin.py
avalara/exceptions.py
avalara/facade.py
avalara/gateway.py
avalara/models.py
avalara/templates/avalara/messages/invalid_address.html
django_oscar_avalara.egg-info/PKG-INFO
django_oscar_avalara.egg-info/SOURCES.txt
django_oscar_avalara.egg-info/dependency_links.txt
django_oscar_avalara.egg-info/requires.txt
django_oscar_avalara.egg-info/top_level.txt