Metadata-Version: 1.1
Name: django-oscar-avalara
Version: 0.2.1
Summary: Avalara integration for django-oscar
Home-page: https://github.com/django-oscar/django-oscar-avalara
Author: David Winterbottom
Author-email: david.winterbottom@gmail.com
License: BSD
Keywords: Taxes,Avalara
Platform: UNKNOWN
Classifier: Development Status :: 4 - Beta
Classifier: Environment :: Web Environment
Classifier: Framework :: Django
Classifier: Intended Audience :: Developers
Classifier: License :: OSI Approved :: BSD License
Classifier: Operating System :: Unix
Classifier: Programming Language :: Python
